pypH.py
pypH-0.2.dist-info/LICENSE
pypH-0.2.dist-info/WHEEL
pypH-0.2.dist-info/METADATA
pypH-0.2.dist-info/RECORD
