Metadata-Version: 2.1
Name: pypH
Version: 0.2
Summary: This takes an argument between 0 and 14 and returns info about that level of pH.
Home-page: https://github.com/boxalarm/pypH/blob/master/pypH.py
License: UNKNOWN
Author: Sam Nachman
Author-email: shnachman1@gmail.com
Classifier: License :: OSI Approved :: MIT License
